dsat/__init__.py
dsat/agents/__init__.py
dsat/agents/agent.py
dsat/agents/agent_experiment.py
dsat/agents/agent_logger.py
dsat/agents/anthropic_agent.py
dsat/agents/litellm_agent.py
dsat/agents/ollama_agent.py
dsat/agents/prompts.py
dsat/agents/vertex_agent.py
dsat/cli/__init__.py
dsat/cli/chat.py
dsat/cli/extensible_memory.py
dsat/cli/main.py
dsat/cli/memory.py
dsat/cli/memory_interfaces.py
dsat/cli/memory_registry.py
dsat/cli/memory_strategies.py
dsat/scryptorum/__init__.py
dsat/scryptorum/cli/__init__.py
dsat/scryptorum/cli/commands.py
dsat/scryptorum/core/__init__.py
dsat/scryptorum/core/config.py
dsat/scryptorum/core/decorators.py
dsat/scryptorum/core/experiment.py
dsat/scryptorum/core/logging_utils.py
dsat/scryptorum/core/project_config.py
dsat/scryptorum/core/runs.py
dsat/scryptorum/execution/__init__.py
dsat/scryptorum/execution/runner.py
dsat/scryptorum/plugins/__init__.py
dsat_ai-0.3.4.dist-info/METADATA
dsat_ai-0.3.4.dist-info/WHEEL
dsat_ai-0.3.4.dist-info/entry_points.txt
dsat_ai-0.3.4.dist-info/licenses/LICENSE
dsat_ai-0.3.4.dist-info/RECORD
