Metadata-Version: 2.4
Name: dsat-ai
Version: 0.3.4
Summary: Dan's Simple Agent Toolkit - Multi-provider LLM agents and experiment tracking
Project-URL: Homepage, https://github.com/ecodan/dsat
Project-URL: Repository, https://github.com/ecodan/dsat
Project-URL: Documentation, https://github.com/ecodan/dsat/blob/main/README.md
Project-URL: Issues, https://github.com/ecodan/dsat/issues
Author-email: Dan <ecodan@hotmail.com>
License: MIT
License-File: LICENSE
Keywords: agents,ai,anthropic,claude,experiments,google,llm,ollama,vertex-ai
Classifier: Development Status :: 4 - Beta
Classifier: Intended Audience :: Developers
Classifier: License :: OSI Approved :: MIT License
Classifier: Programming Language :: Python :: 3
Classifier: Programming Language :: Python :: 3.12
Classifier: Topic :: Scientific/Engineering :: Artificial Intelligence
Classifier: Topic :: Software Development :: Libraries :: Python Modules
Requires-Python: >=3.12
Requires-Dist: aiohttp>=3.8.0
Requires-Dist: colorama>=0.4.0
Requires-Dist: importlib-metadata>=4.0.0; python_version < '3.10'
Requires-Dist: pathlib>=1.0.1
Requires-Dist: python-dotenv>=1.1.0
Requires-Dist: requests>=2.31.0
Requires-Dist: tomlkit>=0.12.0
Provides-Extra: all
Requires-Dist: anthropic>=0.20.0; extra == 'all'
Requires-Dist: google-cloud-aiplatform>=1.40.0; extra == 'all'
Requires-Dist: litellm>=1.40.0; extra == 'all'
Requires-Dist: ollama>=0.1.0; extra == 'all'
Provides-Extra: anthropics
Requires-Dist: anthropic>=0.20.0; extra == 'anthropics'
Provides-Extra: dev
Requires-Dist: aiohttp>=3.8.0; extra == 'dev'
Requires-Dist: black>=23.0.0; extra == 'dev'
Requires-Dist: pytest-asyncio>=0.21.0; extra == 'dev'
Requires-Dist: pytest>=7.0.0; extra == 'dev'
Requires-Dist: ruff>=0.1.0; extra == 'dev'
Provides-Extra: google
Requires-Dist: google-cloud-aiplatform>=1.40.0; extra == 'google'
Provides-Extra: litellm
Requires-Dist: litellm>=1.40.0; extra == 'litellm'
Provides-Extra: ollama
Requires-Dist: ollama>=0.1.0; extra == 'ollama'
Provides-Extra: server
Requires-Dist: fastapi>=0.100.0; extra == 'server'
Requires-Dist: uvicorn>=0.20.0; extra == 'server'
